{"@timestamp":"2020-10-23T18:52:40.887+08:00","traceId":"a77666ed76ff4c128b25fdf179c2bfe2","level":"ERROR","core":"api-mp-manage","host":"192.168.104.200","thread":"http-nio-8899-exec-1","class":"c.s.u.m.c.easyexcel.EasyExcelListener-135","message":"解析excel出错,请传入正确格式的excel,导入标题城市与检查标题序号不匹配","stack_trace":""}
{"@timestamp":"2020-10-23T18:52:40.898+08:00","traceId":"a77666ed76ff4c128b25fdf179c2bfe2","level":"ERROR","core":"api-mp-manage","host":"192.168.104.200","thread":"http-nio-8899-exec-1","class":"c.s.u.m.m.api.base.CarInfoController-191","message":"导入发生错误,解析excel出错,请传入正确格式的excel,导入标题headMap.get(key)与检查标题indexNameMap.get(key)不匹配","stack_trace":"com.alibaba.excel.exception.ExcelAnalysisException: 解析excel出错,请传入正确格式的excel,导入标题headMap.get(key)与检查标题indexNameMap.get(key)不匹配\n\tat com.sq.usercenter.mp.common.easyexcel.EasyExcelListener.invokeHeadMap(EasyExcelListener.java:136)\n\tat com.alibaba.excel.event.AnalysisEventListener.invokeHead(AnalysisEventListener.java:20)\n\tat com.alibaba.excel.read.processor.DefaultAnalysisEventProcessor.dealData(DefaultAnalysisEventProcessor.java:102)\n\tat com.alibaba.excel.read.processor.DefaultAnalysisEventProcessor.endRow(DefaultAnalysisEventProcessor.java:47)\n\tat com.alibaba.excel.analysis.v07.handlers.RowTagHandler.endElement(RowTagHandler.java:47)\n\tat com.alibaba.excel.analysis.v07.handlers.sax.XlsxRowHandler.endElement(XlsxRowHandler.java:89)\n\tat com.sun.org.apache.xerces.internal.parsers.AbstractSAXParser.endElement(AbstractSAXParser.java:609)\n\tat com.sun.org.apache.xerces.internal.impl.XMLDocumentFragmentScannerImpl.scanEndElement(XMLDocumentFragmentScannerImpl.java:1782)\n\tat com.sun.org.apache.xerces.internal.impl.XMLDocumentFragmentScannerImpl$FragmentContentDriver.next(XMLDocumentFragmentScannerImpl.java:2967)\n\tat com.sun.org.apache.xerces.internal.impl.XMLDocumentScannerImpl.next(XMLDocumentScannerImpl.java:602)\n\tat com.sun.org.apache.xerces.internal.impl.XMLDocumentFragmentScannerImpl.scanDocument(XMLDocumentFragmentScannerImpl.java:505)\n\tat com.sun.org.apache.xerces.internal.parsers.XML11Configuration.parse(XML11Configuration.java:841)\n\tat com.sun.org.apache.xerces.internal.parsers.XML11Configuration.parse(XML11Configuration.java:770)\n\tat com.sun.org.apache.xerces.internal.parsers.XMLParser.parse(XMLParser.java:141)\n\tat com.sun.org.apache.xerces.internal.parsers.AbstractSAXParser.parse(AbstractSAXParser.java:1213)\n\tat com.sun.org.apache.xerces.internal.jaxp.SAXParserImpl$JAXPSAXParser.parse(SAXParserImpl.java:643)\n\tat com.alibaba.excel.analysis.v07.XlsxSaxAnalyser.parseXmlSource(XlsxSaxAnalyser.java:178)\n\tat com.alibaba.excel.analysis.v07.XlsxSaxAnalyser.execute(XlsxSaxAnalyser.java:201)\n\tat com.alibaba.excel.analysis.ExcelAnalyserImpl.analysis(ExcelAnalyserImpl.java:115)\n\tat com.alibaba.excel.ExcelReader.read(ExcelReader.java:182)\n\tat com.alibaba.excel.ExcelReader.read(ExcelReader.java:172)\n\tat com.alibaba.excel.read.builder.ExcelReaderSheetBuilder.doRead(ExcelReaderSheetBuilder.java:65)\n\tat com.sq.usercenter.mp.manage.api.base.CarInfoController.importCarExcel(CarInfoController.java:161)\n\tat sun.reflect.NativeMethodAccessorImpl.invoke0(Native Method)\n\tat sun.reflect.NativeMethodAccessorImpl.invoke(NativeMethodAccessorImpl.java:62)\n\tat sun.reflect.DelegatingMethodAccessorImpl.invoke(DelegatingMethodAccessorImpl.java:43)\n\tat java.lang.reflect.Method.invoke(Method.java:498)\n\tat org.springframework.web.method.support.InvocableHandlerMethod.doInvoke(InvocableHandlerMethod.java:209)\n\tat org.springframework.web.method.support.InvocableHandlerMethod.invokeForRequest(InvocableHandlerMethod.java:136)\n\tat org.springframework.web.servlet.mvc.method.annotation.ServletInvocableHandlerMethod.invokeAndHandle(ServletInvocableHandlerMethod.java:102)\n\tat org.springframework.web.servlet.mvc.method.annotation.RequestMappingHandlerAdapter.invokeHandlerMethod(RequestMappingHandlerAdapter.java:877)\n\tat org.springframework.web.servlet.mvc.method.annotation.RequestMappingHandlerAdapter.handleInternal(RequestMappingHandlerAdapter.java:783)\n\tat org.springframework.web.servlet.mvc.method.AbstractHandlerMethodAdapter.handle(AbstractHandlerMethodAdapter.java:87)\n\tat org.springframework.web.servlet.DispatcherServlet.doDispatch(DispatcherServlet.java:991)\n\tat org.springframework.web.servlet.DispatcherServlet.doService(DispatcherServlet.java:925)\n\tat org.springframework.web.servlet.FrameworkServlet.processRequest(FrameworkServlet.java:974)\n\tat org.springframework.web.servlet.FrameworkServlet.doPost(FrameworkServlet.java:877)\n\tat javax.servlet.http.HttpServlet.service(HttpServlet.java:707)\n\tat org.springframework.web.servlet.FrameworkServlet.service(FrameworkServlet.java:851)\n\tat javax.servlet.http.HttpServlet.service(HttpServlet.java:790)\n\tat org.apache.catalina.core.ApplicationFilterChain.internalDoFilter(ApplicationFilterChain.java:231)\n\tat org.apache.catalina.core.ApplicationFilterChain.doFilter(ApplicationFilterChain.java:166)\n\tat org.apache.tomcat.websocket.server.WsFilter.doFilter(WsFilter.java:52)\n\tat org.apache.catalina.core.ApplicationFilterChain.internalDoFilter(ApplicationFilterChain.java:193)\n\tat org.apache.catalina.core.ApplicationFilterChain.doFilter(ApplicationFilterChain.java:166)\n\tat com.github.xiaoymin.swaggerbootstrapui.filter.SecurityBasicAuthFilter.doFilter(SecurityBasicAuthFilter.java:84)\n\tat org.apache.catalina.core.ApplicationFilterChain.internalDoFilter(ApplicationFilterChain.java:193)\n\tat org.apache.catalina.core.ApplicationFilterChain.doFilter(ApplicationFilterChain.java:166)\n\tat com.github.xiaoymin.swaggerbootstrapui.filter.ProductionSecurityFilter.doFilter(ProductionSecurityFilter.java:53)\n\tat org.apache.catalina.core.ApplicationFilterChain.internalDoFilter(ApplicationFilterChain.java:193)\n\tat org.apache.catalina.core.ApplicationFilterChain.doFilter(ApplicationFilterChain.java:166)\n\tat com.sq.usercenter.mp.manage.web.filters.InitRequestCommonDataFilter.doFilterInternal(InitRequestCommonDataFilter.java:29)\n\tat org.springframework.web.filter.OncePerRequestFilter.doFilter(OncePerRequestFilter.java:107)\n\tat org.apache.catalina.core.ApplicationFilterChain.internalDoFilter(ApplicationFilterChain.java:193)\n\tat org.apache.catalina.core.ApplicationFilterChain.doFilter(ApplicationFilterChain.java:166)\n\tat org.springframework.web.filter.RequestContextFilter.doFilterInternal(RequestContextFilter.java:99)\n\tat org.springframework.web.filter.OncePerRequestFilter.doFilter(OncePerRequestFilter.java:107)\n\tat org.apache.catalina.core.ApplicationFilterChain.internalDoFilter(ApplicationFilterChain.java:193)\n\tat org.apache.catalina.core.ApplicationFilterChain.doFilter(ApplicationFilterChain.java:166)\n\tat org.springframework.web.filter.HttpPutFormContentFilter.doFilterInternal(HttpPutFormContentFilter.java:109)\n\tat org.springframework.web.filter.OncePerRequestFilter.doFilter(OncePerRequestFilter.java:107)\n\tat org.apache.catalina.core.ApplicationFilterChain.internalDoFilter(ApplicationFilterChain.java:193)\n\tat org.apache.catalina.core.ApplicationFilterChain.doFilter(ApplicationFilterChain.java:166)\n\tat org.springframework.web.filter.HiddenHttpMethodFilter.doFilterInternal(HiddenHttpMethodFilter.java:93)\n\tat org.springframework.web.filter.OncePerRequestFilter.doFilter(OncePerRequestFilter.java:107)\n\tat org.apache.catalina.core.ApplicationFilterChain.internalDoFilter(ApplicationFilterChain.java:193)\n\tat org.apache.catalina.core.ApplicationFilterChain.doFilter(ApplicationFilterChain.java:166)\n\tat org.springframework.web.filter.CharacterEncodingFilter.doFilterInternal(CharacterEncodingFilter.java:200)\n\tat org.springframework.web.filter.OncePerRequestFilter.doFilter(OncePerRequestFilter.java:107)\n\tat org.apache.catalina.core.ApplicationFilterChain.internalDoFilter(ApplicationFilterChain.java:193)\n\tat org.apache.catalina.core.ApplicationFilterChain.doFilter(ApplicationFilterChain.java:166)\n\tat org.apache.catalina.core.StandardWrapperValve.invoke(StandardWrapperValve.java:198)\n\tat org.apache.catalina.core.StandardContextValve.invoke(StandardContextValve.java:96)\n\tat org.apache.catalina.authenticator.AuthenticatorBase.invoke(AuthenticatorBase.java:496)\n\tat org.apache.catalina.core.StandardHostValve.invoke(StandardHostValve.java:140)\n\tat org.apache.catalina.valves.ErrorReportValve.invoke(ErrorReportValve.java:81)\n\tat org.apache.catalina.core.StandardEngineValve.invoke(StandardEngineValve.java:87)\n\tat org.apache.catalina.valves.AbstractAccessLogValve.invoke(AbstractAccessLogValve.java:650)\n\tat org.apache.catalina.connector.CoyoteAdapter.service(CoyoteAdapter.java:342)\n\tat org.apache.coyote.http11.Http11Processor.service(Http11Processor.java:803)\n\tat org.apache.coyote.AbstractProcessorLight.process(AbstractProcessorLight.java:66)\n\tat org.apache.coyote.AbstractProtocol$ConnectionHandler.process(AbstractProtocol.java:790)\n\tat org.apache.tomcat.util.net.NioEndpoint$SocketProcessor.doRun(NioEndpoint.java:1468)\n\tat org.apache.tomcat.util.net.SocketProcessorBase.run(SocketProcessorBase.java:49)\n\tat java.util.concurrent.ThreadPoolExecutor.runWorker(ThreadPoolExecutor.java:1149)\n\tat java.util.concurrent.ThreadPoolExecutor$Worker.run(ThreadPoolExecutor.java:624)\n\tat org.apache.tomcat.util.threads.TaskThread$WrappingRunnable.run(TaskThread.java:61)\n\tat java.lang.Thread.run(Thread.java:748)\n"}
{"@timestamp":"2020-10-23T18:56:05.499+08:00","traceId":"","level":"ERROR","core":"api-mp-manage","host":"192.168.104.200","thread":"pool-simple-buffer-trigger-thread-0","class":"c.sq.collection.impl.SimpleBufferTrigger-129","message":"Ops.","stack_trace":"java.lang.RuntimeException: org.apache.rocketmq.client.exception.MQClientException: Send [1] times, still failed, cost [34034]ms, Topic: perf, BrokersSent: [broker-a]\nSee http://rocketmq.apache.org/docs/faq/ for further details.\n\tat com.google.common.base.Throwables.propagate(Throwables.java:241)\n\tat com.sq.rocketmq.productor.RocketMqProductorWrap.sendMsg(RocketMqProductorWrap.java:227)\n\tat com.sq.rocketmq.productor.RockectMqProductor.sendMsg(RockectMqProductor.java:57)\n\tat com.sq.rocketmq.productor.RockectMqProductor.sendJson(RockectMqProductor.java:218)\n\tat com.sq.component.utils.speed4j.RocketMqWatchLog.sendPerfToRocketmq(RocketMqWatchLog.java:71)\n\tat com.sq.component.utils.speed4j.RocketMqWatchLog.sendTagToRocket(RocketMqWatchLog.java:45)\n\tat com.sq.component.utils.speed4j.RocketMqWatchLog.displaySingleEntry(RocketMqWatchLog.java:40)\n\tat com.sq.component.utils.speed4j.RocketMqWatchLog.displaySingleEntry(RocketMqWatchLog.java:23)\n\tat java.util.concurrent.ConcurrentHashMap.forEach(ConcurrentHashMap.java:1597)\n\tat com.sq.perf.WatchLog.display(WatchLog.java:66)\n\tat com.sq.component.utils.speed4j.RocketMqWatchLog.display(RocketMqWatchLog.java:35)\n\tat com.sq.collection.impl.SimpleBufferTrigger.doConsume(SimpleBufferTrigger.java:118)\n\tat com.sq.collection.impl.SimpleBufferTrigger.access$500(SimpleBufferTrigger.java:29)\n\tat com.sq.collection.impl.SimpleBufferTrigger$TriggerRunnable.run(SimpleBufferTrigger.java:186)\n\tat java.util.concurrent.Executors$RunnableAdapter.call(Executors.java:511)\n\tat java.util.concurrent.FutureTask.run(FutureTask.java:266)\n\tat java.util.concurrent.ScheduledThreadPoolExecutor$ScheduledFutureTask.access$201(ScheduledThreadPoolExecutor.java:180)\n\tat java.util.concurrent.ScheduledThreadPoolExecutor$ScheduledFutureTask.run(ScheduledThreadPoolExecutor.java:293)\n\tat java.util.concurrent.ThreadPoolExecutor.runWorker(ThreadPoolExecutor.java:1149)\n\tat java.util.concurrent.ThreadPoolExecutor$Worker.run(ThreadPoolExecutor.java:624)\n\tat java.lang.Thread.run(Thread.java:748)\nCaused by: org.apache.rocketmq.client.exception.MQClientException: Send [1] times, still failed, cost [34034]ms, Topic: perf, BrokersSent: [broker-a]\nSee http://rocketmq.apache.org/docs/faq/ for further details.\n\tat org.apache.rocketmq.client.impl.producer.DefaultMQProducerImpl.sendDefaultImpl(DefaultMQProducerImpl.java:544)\n\tat org.apache.rocketmq.client.impl.producer.DefaultMQProducerImpl.send(DefaultMQProducerImpl.java:1069)\n\tat org.apache.rocketmq.client.impl.producer.DefaultMQProducerImpl.send(DefaultMQProducerImpl.java:1023)\n\tat org.apache.rocketmq.client.producer.DefaultMQProducer.send(DefaultMQProducer.java:214)\n\tat com.sq.rocketmq.productor.RocketMqProductorWrap.sendMsg(RocketMqProductorWrap.java:189)\n\t... 19 common frames omitted\nCaused by: org.apache.rocketmq.remoting.exception.RemotingTimeoutException: wait response on the channel <10.0.7.2:10909> timeout, 3000(ms)\n\tat org.apache.rocketmq.remoting.netty.NettyRemotingAbstract.invokeSyncImpl(NettyRemotingAbstract.java:386)\n\tat org.apache.rocketmq.remoting.netty.NettyRemotingClient.invokeSync(NettyRemotingClient.java:369)\n\tat org.apache.rocketmq.client.impl.MQClientAPIImpl.sendMessageSync(MQClientAPIImpl.java:351)\n\tat org.apache.rocketmq.client.impl.MQClientAPIImpl.sendMessage(MQClientAPIImpl.java:335)\n\tat org.apache.rocketmq.client.impl.MQClientAPIImpl.sendMessage(MQClientAPIImpl.java:298)\n\tat org.apache.rocketmq.client.impl.producer.DefaultMQProducerImpl.sendKernelImpl(DefaultMQProducerImpl.java:696)\n\tat org.apache.rocketmq.client.impl.producer.DefaultMQProducerImpl.sendDefaultImpl(DefaultMQProducerImpl.java:463)\n\t... 23 common frames omitted\n"}
{"@timestamp":"2020-10-23T19:14:04.496+08:00","traceId":"00c353efc3d9495b8c5f1496e46142f3","level":"ERROR","core":"api-mp-manage","host":"192.168.104.200","thread":"http-nio-8899-exec-1","class":"c.s.u.mp.manage.web.ControllerException-162","message":"捕获全局异常:","stack_trace":"org.springframework.web.multipart.support.MissingServletRequestPartException: Required request part 'file' is not present\n\tat org.springframework.web.method.annotation.RequestParamMethodArgumentResolver.handleMissingValue(RequestParamMethodArgumentResolver.java:199)\n\tat org.springframework.web.method.annotation.AbstractNamedValueMethodArgumentResolver.resolveArgument(AbstractNamedValueMethodArgumentResolver.java:112)\n\tat org.springframework.web.method.support.HandlerMethodArgumentResolverComposite.resolveArgument(HandlerMethodArgumentResolverComposite.java:124)\n\tat org.springframework.web.method.support.InvocableHandlerMethod.getMethodArgumentValues(InvocableHandlerMethod.java:161)\n\tat org.springframework.web.method.support.InvocableHandlerMethod.invokeForRequest(InvocableHandlerMethod.java:131)\n\tat org.springframework.web.servlet.mvc.method.annotation.ServletInvocableHandlerMethod.invokeAndHandle(ServletInvocableHandlerMethod.java:102)\n\tat org.springframework.web.servlet.mvc.method.annotation.RequestMappingHandlerAdapter.invokeHandlerMethod(RequestMappingHandlerAdapter.java:877)\n\tat org.springframework.web.servlet.mvc.method.annotation.RequestMappingHandlerAdapter.handleInternal(RequestMappingHandlerAdapter.java:783)\n\tat org.springframework.web.servlet.mvc.method.AbstractHandlerMethodAdapter.handle(AbstractHandlerMethodAdapter.java:87)\n\tat org.springframework.web.servlet.DispatcherServlet.doDispatch(DispatcherServlet.java:991)\n\tat org.springframework.web.servlet.DispatcherServlet.doService(DispatcherServlet.java:925)\n\tat org.springframework.web.servlet.FrameworkServlet.processRequest(FrameworkServlet.java:974)\n\tat org.springframework.web.servlet.FrameworkServlet.doPost(FrameworkServlet.java:877)\n\tat javax.servlet.http.HttpServlet.service(HttpServlet.java:707)\n\tat org.springframework.web.servlet.FrameworkServlet.service(FrameworkServlet.java:851)\n\tat javax.servlet.http.HttpServlet.service(HttpServlet.java:790)\n\tat org.apache.catalina.core.ApplicationFilterChain.internalDoFilter(ApplicationFilterChain.java:231)\n\tat org.apache.catalina.core.ApplicationFilterChain.doFilter(ApplicationFilterChain.java:166)\n\tat org.apache.tomcat.websocket.server.WsFilter.doFilter(WsFilter.java:52)\n\tat org.apache.catalina.core.ApplicationFilterChain.internalDoFilter(ApplicationFilterChain.java:193)\n\tat org.apache.catalina.core.ApplicationFilterChain.doFilter(ApplicationFilterChain.java:166)\n\tat com.github.xiaoymin.swaggerbootstrapui.filter.SecurityBasicAuthFilter.doFilter(SecurityBasicAuthFilter.java:84)\n\tat org.apache.catalina.core.ApplicationFilterChain.internalDoFilter(ApplicationFilterChain.java:193)\n\tat org.apache.catalina.core.ApplicationFilterChain.doFilter(ApplicationFilterChain.java:166)\n\tat com.github.xiaoymin.swaggerbootstrapui.filter.ProductionSecurityFilter.doFilter(ProductionSecurityFilter.java:53)\n\tat org.apache.catalina.core.ApplicationFilterChain.internalDoFilter(ApplicationFilterChain.java:193)\n\tat org.apache.catalina.core.ApplicationFilterChain.doFilter(ApplicationFilterChain.java:166)\n\tat com.sq.usercenter.mp.manage.web.filters.InitRequestCommonDataFilter.doFilterInternal(InitRequestCommonDataFilter.java:29)\n\tat org.springframework.web.filter.OncePerRequestFilter.doFilter(OncePerRequestFilter.java:107)\n\tat org.apache.catalina.core.ApplicationFilterChain.internalDoFilter(ApplicationFilterChain.java:193)\n\tat org.apache.catalina.core.ApplicationFilterChain.doFilter(ApplicationFilterChain.java:166)\n\tat org.springframework.web.filter.RequestContextFilter.doFilterInternal(RequestContextFilter.java:99)\n\tat org.springframework.web.filter.OncePerRequestFilter.doFilter(OncePerRequestFilter.java:107)\n\tat org.apache.catalina.core.ApplicationFilterChain.internalDoFilter(ApplicationFilterChain.java:193)\n\tat org.apache.catalina.core.ApplicationFilterChain.doFilter(ApplicationFilterChain.java:166)\n\tat org.springframework.web.filter.HttpPutFormContentFilter.doFilterInternal(HttpPutFormContentFilter.java:109)\n\tat org.springframework.web.filter.OncePerRequestFilter.doFilter(OncePerRequestFilter.java:107)\n\tat org.apache.catalina.core.ApplicationFilterChain.internalDoFilter(ApplicationFilterChain.java:193)\n\tat org.apache.catalina.core.ApplicationFilterChain.doFilter(ApplicationFilterChain.java:166)\n\tat org.springframework.web.filter.HiddenHttpMethodFilter.doFilterInternal(HiddenHttpMethodFilter.java:93)\n\tat org.springframework.web.filter.OncePerRequestFilter.doFilter(OncePerRequestFilter.java:107)\n\tat org.apache.catalina.core.ApplicationFilterChain.internalDoFilter(ApplicationFilterChain.java:193)\n\tat org.apache.catalina.core.ApplicationFilterChain.doFilter(ApplicationFilterChain.java:166)\n\tat org.springframework.web.filter.CharacterEncodingFilter.doFilterInternal(CharacterEncodingFilter.java:200)\n\tat org.springframework.web.filter.OncePerRequestFilter.doFilter(OncePerRequestFilter.java:107)\n\tat org.apache.catalina.core.ApplicationFilterChain.internalDoFilter(ApplicationFilterChain.java:193)\n\tat org.apache.catalina.core.ApplicationFilterChain.doFilter(ApplicationFilterChain.java:166)\n\tat org.apache.catalina.core.StandardWrapperValve.invoke(StandardWrapperValve.java:198)\n\tat org.apache.catalina.core.StandardContextValve.invoke(StandardContextValve.java:96)\n\tat org.apache.catalina.authenticator.AuthenticatorBase.invoke(AuthenticatorBase.java:496)\n\tat org.apache.catalina.core.StandardHostValve.invoke(StandardHostValve.java:140)\n\tat org.apache.catalina.valves.ErrorReportValve.invoke(ErrorReportValve.java:81)\n\tat org.apache.catalina.core.StandardEngineValve.invoke(StandardEngineValve.java:87)\n\tat org.apache.catalina.valves.AbstractAccessLogValve.invoke(AbstractAccessLogValve.java:650)\n\tat org.apache.catalina.connector.CoyoteAdapter.service(CoyoteAdapter.java:342)\n\tat org.apache.coyote.http11.Http11Processor.service(Http11Processor.java:803)\n\tat org.apache.coyote.AbstractProcessorLight.process(AbstractProcessorLight.java:66)\n\tat org.apache.coyote.AbstractProtocol$ConnectionHandler.process(AbstractProtocol.java:790)\n\tat org.apache.tomcat.util.net.NioEndpoint$SocketProcessor.doRun(NioEndpoint.java:1468)\n\tat org.apache.tomcat.util.net.SocketProcessorBase.run(SocketProcessorBase.java:49)\n\tat java.util.concurrent.ThreadPoolExecutor.runWorker(ThreadPoolExecutor.java:1149)\n\tat java.util.concurrent.ThreadPoolExecutor$Worker.run(ThreadPoolExecutor.java:624)\n\tat org.apache.tomcat.util.threads.TaskThread$WrappingRunnable.run(TaskThread.java:61)\n\tat java.lang.Thread.run(Thread.java:748)\n"}
{"@timestamp":"2020-10-23T19:14:55.194+08:00","traceId":"","level":"ERROR","core":"api-mp-manage","host":"192.168.104.200","thread":"pool-simple-buffer-trigger-thread-0","class":"c.sq.collection.impl.SimpleBufferTrigger-129","message":"Ops.","stack_trace":"java.lang.RuntimeException: org.apache.rocketmq.client.exception.MQClientException: No route info of this topic, perf\nSee http://rocketmq.apache.org/docs/faq/ for further details.\n\tat com.google.common.base.Throwables.propagate(Throwables.java:241)\n\tat com.sq.rocketmq.productor.RocketMqProductorWrap.sendMsg(RocketMqProductorWrap.java:227)\n\tat com.sq.rocketmq.productor.RockectMqProductor.sendMsg(RockectMqProductor.java:57)\n\tat com.sq.rocketmq.productor.RockectMqProductor.sendJson(RockectMqProductor.java:218)\n\tat com.sq.component.utils.speed4j.RocketMqWatchLog.sendPerfToRocketmq(RocketMqWatchLog.java:71)\n\tat com.sq.component.utils.speed4j.RocketMqWatchLog.sendTagToRocket(RocketMqWatchLog.java:45)\n\tat com.sq.component.utils.speed4j.RocketMqWatchLog.displaySingleEntry(RocketMqWatchLog.java:40)\n\tat com.sq.component.utils.speed4j.RocketMqWatchLog.displaySingleEntry(RocketMqWatchLog.java:23)\n\tat java.util.concurrent.ConcurrentHashMap.forEach(ConcurrentHashMap.java:1597)\n\tat com.sq.perf.WatchLog.display(WatchLog.java:66)\n\tat com.sq.component.utils.speed4j.RocketMqWatchLog.display(RocketMqWatchLog.java:35)\n\tat com.sq.collection.impl.SimpleBufferTrigger.doConsume(SimpleBufferTrigger.java:118)\n\tat com.sq.collection.impl.SimpleBufferTrigger.access$500(SimpleBufferTrigger.java:29)\n\tat com.sq.collection.impl.SimpleBufferTrigger$TriggerRunnable.run(SimpleBufferTrigger.java:186)\n\tat java.util.concurrent.Executors$RunnableAdapter.call(Executors.java:511)\n\tat java.util.concurrent.FutureTask.run(FutureTask.java:266)\n\tat java.util.concurrent.ScheduledThreadPoolExecutor$ScheduledFutureTask.access$201(ScheduledThreadPoolExecutor.java:180)\n\tat java.util.concurrent.ScheduledThreadPoolExecutor$ScheduledFutureTask.run(ScheduledThreadPoolExecutor.java:293)\n\tat java.util.concurrent.ThreadPoolExecutor.runWorker(ThreadPoolExecutor.java:1149)\n\tat java.util.concurrent.ThreadPoolExecutor$Worker.run(ThreadPoolExecutor.java:624)\n\tat java.lang.Thread.run(Thread.java:748)\nCaused by: org.apache.rocketmq.client.exception.MQClientException: No route info of this topic, perf\nSee http://rocketmq.apache.org/docs/faq/ for further details.\n\tat org.apache.rocketmq.client.impl.producer.DefaultMQProducerImpl.sendDefaultImpl(DefaultMQProducerImpl.java:564)\n\tat org.apache.rocketmq.client.impl.producer.DefaultMQProducerImpl.send(DefaultMQProducerImpl.java:1069)\n\tat org.apache.rocketmq.client.impl.producer.DefaultMQProducerImpl.send(DefaultMQProducerImpl.java:1023)\n\tat org.apache.rocketmq.client.producer.DefaultMQProducer.send(DefaultMQProducer.java:214)\n\tat com.sq.rocketmq.productor.RocketMqProductorWrap.sendMsg(RocketMqProductorWrap.java:189)\n\t... 19 common frames omitted\n"}
